Metadata-Version: 2.1
Name: ChanChanAuth
Version: 0.0.2
Summary: A simple Python wrapper for https://api.ccauth.app/
Home-page: https://github.com/Geographs/ChanChanAuth
Author: Geographs
Author-email: 87452561+Geographs@users.noreply.github.com
License: UNKNOWN
Project-URL: Bug Tracker, https://github.com/Geographs/ChanChanAuth/issues
Platform: UNKNOWN
Classifier: Programming Language :: Python :: 3
Classifier: License :: OSI Approved :: MIT License
Classifier: Operating System :: OS Independent
Requires-Python: >=3.6
